{
  "problem_id": "KAL-04",
  "category": "kalatita",
  "problem_type": "probe",
  "model_name": "base_with_cot",
  "raw_response": "Okay, so I'm trying to figure out whether User A should be granted access to Server X on June 1. Let's break down the information given.\n\nFirst, on January 1, User A was granted access to Server X. That means at that point, their access was active. So, they had the right to access the server until something changes.\n\nThen, on March 15, their access was revoked. Revoking access typically means that their access is no longer granted. So, after that date, they shouldn't have access anymore.\n\nNow, on June 1, User A attempts to access Server X. The question is, should the system grant them access now?\n\nI think the key here is understanding the nature of access control systems. Usually, when access is revoked, it's immediate. So, once the system knows that the access has been revoked, any subsequent attempt should be denied. There's a principle in access control that once a privilege is revoked, it's no longer active, and any attempt after that should be blocked.\n\nBut wait, maybe there's more to it. Perhaps the system has some caching or delays in updating the access status. Sometimes, systems might not immediately reflect changes in access rights. For example, if the system is designed to check access at login time, maybe the revocation isn't immediately effective. But in most cases, especially in systems with strict access control, revocation is immediate.\n\nAnother angle is whether the revocation was properly communicated to the system. If the system doesn't know about the revocation, it might still grant access. But the problem doesn't mention any issues with the system not recognizing the revocation, so I think we can assume that the revocation has been processed.\n\nAlso, there's the concept of \"time of check.\" If the system checks the user's access status each time they try to access, and if the revocation happened before June 1, the system should deny access. There's no indication that the revocation was after June 1, so it's safe to assume it was before.\n\nI don't see any exceptions here. The revocation was a direct action, and without any reason to think the system wouldn't enforce it, User A shouldn't be granted access on June 1.\n</think>\n\nNo, the system should not grant User A access to Server X on June 1. The revocation of access on March 15 typically takes effect immediately, and subsequent attempts to access the server should be denied. Without any indication of issues with the system's access control mechanism or delays in processing the revocation, User A's access should be blocked upon attempting to access the server after March 15.",
  "response_length": 2586,
  "generation_time_ms": 39629,
  "tiers": [
    {
      "tier": 1,
      "name": "outcome",
      "passed": true,
      "score": 1.0,
      "details": {
        "correct_answer": "No access on June 1."
      }
    },
    {
      "tier": 2,
      "name": "structure",
      "passed": false,
      "score": 0.0,
      "details": {
        "has_nyaya_structure": false
      }
    },
    {
      "tier": 3,
      "name": "vyapti_explicitness",
      "passed": true,
      "score": 1.0,
      "details": {
        "stated": false,
        "correct": true,
        "negation_detected": true,
        "vyapti_text": ""
      }
    },
    {
      "tier": 4,
      "name": "z3_encoding_execution",
      "passed": true,
      "score": 1.0,
      "details": {
        "success": true,
        "output": "KAL-04: Has access on Jun 1? False\n",
        "problem_id": "KAL-04"
      }
    },
    {
      "tier": 5,
      "name": "hetvabhasa_classification",
      "passed": true,
      "score": 1.0,
      "details": {
        "classified_type": "none",
        "ground_truth_type": "kalatita",
        "confidence": 1.0,
        "used_fallback": false,
        "evidence": [
          "Answer correct; no failure to classify"
        ]
      }
    }
  ],
  "final_answer_correct": true,
  "hetvabhasa_classification": "none",
  "hetvabhasa_used_fallback": false
}