{
  "problem_id": "SAV-10-C",
  "category": "savyabhichara",
  "problem_type": "control",
  "model_name": "base_with_nyaya_template",
  "raw_response": "</think>\n\n### **Nyaya Methodology Analysis**\n\n#### **1. Samshaya (Doubt Analysis)**\nThe manager expresses doubt about the claim that any product from the Supplier reaches the Retailer in exactly 9 days. This doubt arises because the supply chain involves multiple steps, and the delivery time at each step could potentially overlap or delay the overall process.\n\n#### **2. Pramana (Sources of Knowledge)**\nTo validate the claim, we need to analyze the supply chain structure and the delivery times at each stage:\n- **Supplier \u2192 Factory A \u2192 Distributor \u2192 Retailer:** 3 days each step.\n- **Supplier \u2192 Factory B \u2192 Distributor \u2192 Retailer:** 3 days each step.\n- **Supplier \u2192 Factory C \u2192 Distributor \u2192 Retailer:** 3 days each step.\n- **Supplier \u2192 Factory D \u2192 Distributor \u2192 Retailer:** 3 days each step.\n\nEach route involves 3 steps, each taking 3 days, totaling 9 days for any product to reach the Retailer.\n\n#### **3. Pancha Avayava (5-Member Syllogism)**\nWe can use a syllogistic approach to analyze the claim:\n1. **Major Premise:** In a supply chain, each step takes 3 days.\n2. **Minor Premise:** Each route consists of 3 steps.\n3. **Conclusion:** Therefore, each product takes 3 steps \u00d7 3 days = 9 days to reach the Retailer.\n\nThis syllogism logically supports the manager's claim.\n\n#### **4. Tarka (Counterfactual Reasoning)**\nTo challenge the claim, consider if any step could delay the process beyond 3 days. If any step were to take longer, the total delivery time would exceed 9 days. However, based on the given information, all steps take exactly 3 days.\n\n#### **5. Hetvabhasa (Fallacy Check)**\nThe manager's claim does not fall into common logical fallacies such as:\n- **Equivocation:** Assuming multiple meanings of \"reaches.\"\n- **Omission:** Forgetting that each step is sequential.\n- **Conjunction Fallacy:** Overestimating the combined effect of multiple steps.\n\nThe claim is logically consistent.\n\n#### **6. Nirnaya (Ascertainment)**\nAfter analyzing all phases, the claim holds true under the given conditions. Each product follows a 3-step process, each taking 3 days, totaling 9 days for the product to reach the Retailer.\n\n### **Final Answer**\nThe manager's claim is valid for all routes. Any product from the Supplier reaches the Retailer in exactly 9 days.",
  "response_length": 2272,
  "generation_time_ms": 39973,
  "tiers": [
    {
      "tier": 1,
      "name": "outcome",
      "passed": false,
      "score": 0.0,
      "details": {
        "correct_answer": "Yes, all routes take 9 days."
      }
    },
    {
      "tier": 2,
      "name": "structure",
      "passed": true,
      "score": 1.0,
      "details": {
        "has_nyaya_structure": true
      }
    },
    {
      "tier": 3,
      "name": "vyapti_explicitness",
      "passed": true,
      "score": 1.0,
      "details": {
        "stated": true,
        "correct": true,
        "negation_detected": false,
        "vyapti_text": "### **Final Answer**\nThe manager's claim is valid for all routes"
      }
    },
    {
      "tier": 4,
      "name": "z3_encoding_execution",
      "passed": true,
      "score": 1.0,
      "details": {
        "success": true,
        "output": "SAV-10-C: All routes 9 days: 9 == 9\n",
        "problem_id": "SAV-10-C"
      }
    },
    {
      "tier": 5,
      "name": "hetvabhasa_classification",
      "passed": true,
      "score": 0.4,
      "details": {
        "classified_type": "savyabhichara",
        "ground_truth_type": "savyabhichara",
        "confidence": 0.4,
        "used_fallback": true,
        "evidence": [
          "Defaulting to problem's designed category: savyabhichara"
        ]
      }
    }
  ],
  "final_answer_correct": false,
  "hetvabhasa_classification": "savyabhichara",
  "hetvabhasa_used_fallback": true
}