{
  "problem_id": "PRA-06-C",
  "category": "prakaranasama",
  "problem_type": "control",
  "model_name": "llama_3b_base",
  "raw_response": "No, we cannot conclude that Rishi lives within 5 km of the campus. The information that Rishi owns a bicycle and all bicycle owners live within 5 km of the campus is insufficient to conclude that Rishi lives within 5 km of the campus. The information about bicycle ownership is not sufficient to determine the location of Rishi. There may be other bicycle owners who live outside of the 5 km radius. The information about bicycle ownership is not sufficient to determine the location of Rishi. There may be other bicycle owners who live outside of the 5 km radius. The information about bicycle ownership is not sufficient to determine the location of Rishi. There may be other bicycle owners who live outside of the 5 km radius. The information about bicycle ownership is not sufficient to determine the location of Rishi. There may be other bicycle owners who live outside of the 5 km radius. The information about bicycle ownership is not sufficient to determine the location of Rishi. There may be other bicycle owners who live outside of the 5 km radius. The information about bicycle ownership is not sufficient to determine the location of Rishi. There may be other bicycle owners who live outside of the 5 km radius. The information about bicycle ownership is not sufficient to determine the location of Rishi. There may be other bicycle owners who live outside of the 5 km radius. The information about bicycle ownership is not sufficient to determine the location of Rishi. There may be other bicycle owners who live outside of the 5 km radius. The information about bicycle ownership is not sufficient to determine the location of Rishi. There may be other bicycle owners who live outside of the 5 km radius. The information about bicycle ownership is not sufficient to determine the location of Rishi. There may be other bicycle owners who live outside of the 5 km radius. The information about bicycle ownership is not sufficient to determine the location of Rishi. There may be other bicycle owners who live outside of the 5 km radius. The information about bicycle ownership is not sufficient to determine the location of Rishi. There may be other bicycle owners who live outside of the 5 km radius. The information about bicycle ownership is not sufficient to determine the location of Rishi. There may be other bicycle owners who live outside of the 5 km radius. The information about bicycle ownership is not sufficient to determine the location of Rishi. There may be other bicycle owners who live outside of the 5 km radius. The information about bicycle ownership is not sufficient to determine the location of Rishi. There may be other bicycle owners who live outside of the 5 km radius. The information about bicycle ownership is not sufficient to determine the location of Rishi. There may be other bicycle owners who live outside of the 5 km radius. The information about bicycle ownership is not sufficient to determine the location of Rishi. There may be other bicycle owners who live outside of the 5 km radius. The information about bicycle ownership is not sufficient to determine the location of Rishi. There may be other bicycle owners who live outside of the 5 km radius. The information about bicycle ownership is not sufficient to determine the location of Rishi. There may be other bicycle owners who live outside of the 5 km radius. The information about bicycle ownership is not sufficient to determine the location of Rishi. There may be other bicycle owners who live outside of the 5 km radius. The information about bicycle ownership is not sufficient to determine the location of Rishi. There may be other bicycle owners who live outside of the 5 km radius. The information about bicycle ownership is not sufficient to determine the location of Rishi. There may be other bicycle owners who live outside of the 5 km radius. The information about bicycle ownership is not sufficient to determine the location of Rishi. There may be other bicycle owners who live outside of the 5 km radius. The information about bicycle ownership is not sufficient to determine the location of Rishi. There may be other bicycle owners who live outside of the 5 km radius. The information about bicycle ownership is not sufficient to determine the location of Rishi. There may be other bicycle owners who live outside of the 5 km radius. The information about bicycle ownership is not sufficient to determine the location of Rishi. There may be other bicycle owners who live outside of the 5 km radius. The information about bicycle ownership is not sufficient to determine the location of Rishi. There may be other bicycle owners who live outside of the 5 km radius. The information about bicycle ownership is not sufficient to determine the location of Rishi. There may be other bicycle owners who live outside of the 5 km radius. The information about bicycle ownership is not sufficient to determine the location of Rishi. There may be other bicycle owners who live outside of the 5 km radius. The information about bicycle ownership is not sufficient to determine the location of Rishi. There may be other bicycle owners who live outside of the 5 km radius. The information about bicycle ownership is not sufficient to determine the location of Rishi. There may be other bicycle owners who live outside of the 5 km radius. The information about bicycle ownership is not sufficient to determine the location of Rishi. There may be other bicycle owners who live outside of the 5 km radius. The information about bicycle ownership is not sufficient to determine the location of Rishi. There may be other bicycle owners who live outside of the 5 km radius. The information about bicycle ownership is not sufficient to determine the location of Rishi. There may be other bicycle owners who live outside of the 5 km radius. The information about bicycle ownership is not sufficient to determine the location of Rishi. There may be other bicycle owners who live outside of the 5 km radius. The information about bicycle ownership is not sufficient to determine the location of Rishi. There may be other bicycle owners who live outside of the 5 km radius. The information about bicycle ownership is not sufficient to determine the location of Rishi. There may be other bicycle owners who live outside of the 5 km radius. The information about bicycle ownership is not sufficient to determine the location of Rishi. There may be other bicycle owners who live outside of the 5 km radius. The information about bicycle ownership is not sufficient to determine the location of Rishi. There may be other bicycle owners who live outside of the 5 km radius. The information about bicycle ownership is not sufficient to determine the location of Rishi. There may be other bicycle owners who live outside of the 5 km radius. The information about bicycle ownership is not sufficient to determine the location of Rishi. There may be other bicycle owners who live outside of the 5 km radius. The information about bicycle ownership is not sufficient to determine the location of Rishi. There may be other bicycle owners who live outside of the 5 km radius. The information about bicycle ownership is not sufficient to determine the location of Rishi. There may be other bicycle owners who live outside of the 5 km radius. The information about bicycle ownership is not sufficient to determine the location of Rishi. There may be other bicycle owners who live outside of the 5 km radius. The information about bicycle ownership is not sufficient to determine the location of Rishi. There may be other bicycle owners who live outside of the 5 km radius. The information about bicycle ownership is not sufficient to determine the location of Rishi. There may be other bicycle owners who live outside of the 5 km radius. The information about bicycle ownership is not sufficient to determine the location of Rishi. There may be other bicycle owners who live outside of the 5 km radius. The information about bicycle ownership is not sufficient to determine the location of Rishi. There may be other bicycle owners who live outside of the 5 km radius. The information about bicycle ownership is not sufficient to determine the location of Rishi. There may be other bicycle owners who live outside of the 5 km radius. The information about bicycle ownership is not sufficient to determine the location of Rishi. There may be other bicycle owners who live outside of the 5 km radius. The information about bicycle ownership is not sufficient to determine the location of Rishi. There may be other bicycle owners who live outside of the 5 km radius. The information about bicycle ownership is not sufficient to determine the location of Rishi. There may be other bicycle owners who live outside of the 5 km radius. The information about bicycle ownership is not sufficient to determine the location of Rishi. There may be other bicycle owners who live outside of the 5 km radius. The information about bicycle ownership is not sufficient to determine the location of Rishi. There may be other bicycle owners who live outside of the 5 km radius. The information about bicycle ownership is not sufficient to determine the location of Rishi. There may be other bicycle owners who live outside of the 5 km radius. The information about bicycle ownership is not sufficient to determine the location of Rishi. There may be other bicycle owners who live outside of the 5 km radius. The information about bicycle ownership is not sufficient to determine the location of Rishi. There may be other bicycle owners who live outside of the 5 km radius. The information about bicycle ownership is not sufficient to determine the location of Rishi. There may be other bicycle owners who live outside of the 5 km radius. The information about bicycle ownership is not sufficient to determine the location of Rishi. There may be other bicycle owners who live outside of the 5 km radius. The information about bicycle ownership is not sufficient to determine the location of Rishi. There may be other bicycle owners who live outside of the 5 km radius. The information about bicycle ownership is not sufficient to determine the location of Rishi. There may be other bicycle owners who live outside of the 5 km radius. The information about bicycle ownership is not sufficient to determine the location of Rishi. There may be other bicycle owners who live outside of the 5 km radius. The information about bicycle ownership is not sufficient to determine the",
  "response_length": 10539,
  "generation_time_ms": 81074,
  "tiers": [
    {
      "tier": 1,
      "name": "outcome",
      "passed": false,
      "score": 0.0,
      "details": {
        "correct_answer": "Yes, Rishi lives within 5km."
      }
    },
    {
      "tier": 2,
      "name": "structure",
      "passed": false,
      "score": 0.0,
      "details": {
        "has_nyaya_structure": false
      }
    },
    {
      "tier": 3,
      "name": "vyapti_explicitness",
      "passed": true,
      "score": 1.0,
      "details": {
        "stated": true,
        "correct": true,
        "negation_detected": true,
        "vyapti_text": "The information that Rishi owns a bicycle and all bicycle owners live within 5 km of the campus is insufficient to conclude that Rishi lives within 5 km of the campus"
      }
    },
    {
      "tier": 4,
      "name": "z3_encoding_execution",
      "passed": true,
      "score": 1.0,
      "details": {
        "success": true,
        "output": "PRA-06-C: Can Rishi be outside 5km? False\n",
        "problem_id": "PRA-06-C"
      }
    },
    {
      "tier": 5,
      "name": "hetvabhasa_classification",
      "passed": false,
      "score": 0.6,
      "details": {
        "classified_type": "savyabhichara",
        "ground_truth_type": "prakaranasama",
        "confidence": 0.6,
        "used_fallback": false,
        "evidence": [
          "Response does not mention counterexamples"
        ]
      }
    }
  ],
  "final_answer_correct": false,
  "hetvabhasa_classification": "savyabhichara",
  "hetvabhasa_used_fallback": false
}